{
    "서울": {
        "도심권": 2043.4,
        "동북권": 1332.5,
        "동남권": 2475.0,
        "서북권": 1611.6,
        "서남권": 1432.1,
        "서울": 1742.7
    },
    "경기": {
        "경기": 760.1
    },
    "부산": {
        "부산": 501.6
    },
    "대구": {
        "대구": 646.3
    },
    "인천": {
        "인천": 738.4
    },
    "광주": {
        "광주": 737.2
    },
    "대전": {
        "대전": 768.6
    },
    "울산": {
        "울산": 703.6
    },
    "세종": {
        "세종": 866.8
    },
    "강원": {
        "강원": 495.4
    },
    "충북": {
        "충북": 400.5
    },
    "충남": {
        "충남": 460.8
    },
    "전북": {
        "전북": 405.2
    },
    "전남": {
        "전남": 428.7
    },
    "경북": {
        "경북": 387.1
    },
    "경남": {
        "경남": 490.7
    },
    "제주": {
        "제주": 739.1
    }
}